setup.py
quantcluster/__init__.py
quantcluster.egg-info/PKG-INFO
quantcluster.egg-info/SOURCES.txt
quantcluster.egg-info/dependency_links.txt
quantcluster.egg-info/requires.txt
quantcluster.egg-info/top_level.txt
quantcluster/plugins/__init__.py
quantcluster/plugins/django.py
quantcluster/plugins/hadoop.py
quantcluster/plugins/hbase.py
quantcluster/plugins/hive.py
quantcluster/plugins/quant_cluster.py