Metadata-Version: 1.0
Name: quantcluster
Version: 0.0.2
Summary: A command line interface for QF cluster-computing on AWS EC2.
Home-page: http://www.goodeanalytics.com
Author: Jimmie Goode
Author-email: jimmie@goodeanalytics.com
License: UNKNOWN
Platform: UNKNOWN
